primePN/primo.py
primePN-3.0.dist-info/LICENSE.txt
primePN-3.0.dist-info/METADATA
primePN-3.0.dist-info/WHEEL
primePN-3.0.dist-info/top_level.txt
primePN-3.0.dist-info/RECORD
