Metadata-Version: 2.1
Name: primePN
Version: 3.0
Summary: A tool to check the prime numbers between 1 and n.
Home-page: UNKNOWN
Author: Pedro Navarro
Author-email: petrus_nvm@hotmail.com
License: GNU GPLv3
Keywords: prime primo primenumber
Platform: UNKNOWN
Classifier: Development Status :: 4 - Beta
Classifier: Intended Audience :: Developers
Classifier: Topic :: Utilities
Classifier: License :: OSI Approved :: GNU General Public License v3 (GPLv3)
Classifier: Programming Language :: Python :: 3
Classifier: Operating System :: OS Independent
License-File: LICENSE.txt
